COPYRIGHT.txt
LICENSE.txt
MANIFEST.in
README.rst
setup.py
Products/__init__.py
Products.LongRequestLogger.egg-info/PKG-INFO
Products.LongRequestLogger.egg-info/SOURCES.txt
Products.LongRequestLogger.egg-info/dependency_links.txt
Products.LongRequestLogger.egg-info/namespace_packages.txt
Products.LongRequestLogger.egg-info/not-zip-safe
Products.LongRequestLogger.egg-info/requires.txt
Products.LongRequestLogger.egg-info/top_level.txt
Products/LongRequestLogger/__init__.py
Products/LongRequestLogger/dumper.py
Products/LongRequestLogger/monitor.py
Products/LongRequestLogger/version.txt
Products/LongRequestLogger/tests/__init__.py
Products/LongRequestLogger/tests/common.py
Products/LongRequestLogger/tests/testLongRequestLogger.py
docs/HISTORY.rst