Metadata-Version: 1.1
Name: Products.LongRequestLogger
Version: 2.1.0
Summary: Dumps sequential stack traces of long-running Zope2 requests
Home-page: https://github.com/zopefoundation/Products.LongRequestLogger
Author: Nexedi SA
Author-email: erp5-dev@erp5.org
License: ZPL
Keywords: performance zope2 plone erp5
Platform: UNKNOWN
Classifier: Programming Language :: Python
Classifier: Framework :: Zope2
Classifier: Intended Audience :: System Administrators
